fluxgate/__init__.py
fluxgate/circuitbreaker.py
fluxgate/errors.py
fluxgate/interfaces.py
fluxgate/metric.py
fluxgate/permits.py
fluxgate/py.typed
fluxgate/retries.py
fluxgate/signal.py
fluxgate/state.py
fluxgate/trackers.py
fluxgate/trippers.py
fluxgate/windows.py
fluxgate/listeners/__init__.py
fluxgate/listeners/log.py
fluxgate/listeners/prometheus.py
fluxgate/listeners/slack.py
fluxgate-0.6.0.dist-info/METADATA
fluxgate-0.6.0.dist-info/WHEEL
fluxgate-0.6.0.dist-info/licenses/LICENSE
fluxgate-0.6.0.dist-info/RECORD
