Metadata-Version: 2.4
Name: fluxgate
Version: 0.6.0
Summary: A modern, composable circuit breaker library for Python
Project-URL: Homepage, https://github.com/byExist/fluxgate
Project-URL: Documentation, https://byExist.github.io/fluxgate
Project-URL: Repository, https://github.com/byExist/fluxgate
Project-URL: Changelog, https://byExist.github.io/fluxgate/changelog/
Author-email: Jongbeom Kwon <jongbeom.kwon@gmail.com>
License: MIT
License-File: LICENSE
Keywords: async,circuit-breaker,fault-tolerance,resilience
Classifier: Development Status :: 4 - Beta
Classifier: Intended Audience :: Developers
Classifier: License :: OSI Approved :: MIT License
Classifier: Programming Language :: Python :: 3
Classifier: Programming Language :: Python :: 3.10
Classifier: Programming Language :: Python :: 3.11
Classifier: Programming Language :: Python :: 3.12
Classifier: Programming Language :: Python :: 3.13
Classifier: Topic :: Software Development :: Libraries :: Python Modules
Classifier: Typing :: Typed
Requires-Python: >=3.10
Requires-Dist: typing-extensions~=4.15; python_version < '3.11'
Provides-Extra: all
Requires-Dist: httpx~=0.28; extra == 'all'
Requires-Dist: prometheus-client~=0.23; extra == 'all'
Provides-Extra: prometheus
Requires-Dist: prometheus-client~=0.23; extra == 'prometheus'
Provides-Extra: slack
Requires-Dist: httpx~=0.28; extra == 'slack'
